README.txt
setup.py
TextShaper.egg-info/PKG-INFO
TextShaper.egg-info/SOURCES.txt
TextShaper.egg-info/dependency_links.txt
TextShaper.egg-info/entry_points.txt
TextShaper.egg-info/not-zip-safe
TextShaper.egg-info/requires.txt
TextShaper.egg-info/top_level.txt
textshaper/__init__.py
textshaper/commands.py
textshaper/decorator.py
textshaper/indent.py
textshaper/main.py
textshaper/onelineit.py
textshaper/quote.py
textshaper/tablify.py
textshaper/url2txt.py
textshaper/web.py
textshaper/whitespace.py