Metadata-Version: 1.0
Name: TextShaper
Version: 0.0
Summary: package to shape text blocks 
Home-page: http://k0s.org/hg/TextShaper
Author: Jeff Hammel
Author-email: k0scist@gmail.com
License: MPL2
Platform: UNKNOWN
